{
  "fontsource-roboto": 96983,
  "@fontsource/roboto": 52271,
  "fontsource-inter": 30776,
  "fontsource-fira-code": 27166,
  "@fontsource/open-sans": 19919,
  "fontsource-open-sans": 15736,
  "@fontsource/lato": 12680,
  "@fontsource/inter": 11794,
  "fontsource-poppins": 11326,
  "@fontsource/montserrat": 10665,
  "@fontsource/poppins": 9661,
  "fontsource-mulish": 8638,
  "fontsource-lato": 7409,
  "@fontsource/nunito": 7342,
  "@fontsource/noto-sans": 7120,
  "@fontsource/roboto-mono": 6766,
  "@fontsource/source-sans-pro": 6403,
  "@fontsource/spartan": 6395,
  "@fontsource/ubuntu": 5700,
  "@fontsource/noto-sans-jp": 5415,
  "fontsource-titillium-web": 5116,
  "fontsource-montserrat": 5103,
  "@fontsource/noto-sans-kr": 4612,
  "@fontsource/noto-sans-sc": 4549,
  "@fontsource/noto-sans-hk": 4486,
  "fontsource-roboto-mono": 4187,
  "fontsource-source-sans-pro": 3503,
  "@fontsource/raleway": 3324,
  "fontsource-rubik": 3135,
  "@fontsource/material-icons": 3045,
  "@fontsource/nunito-sans": 3026,
  "@fontsource/permanent-marker": 2649,
  "@fontsource/roboto-slab": 2646,
  "fontsource-overpass": 2331,
  "@fontsource/rubik": 2297,
  "@fontsource/roboto-condensed": 2237,
  "@fontsource/noto-sans-tc": 2030,
  "fontsource-work-sans": 1971,
  "fontsource-noto-sans-jp": 1811,
  "fontsource-ubuntu": 1793,
  "@fontsource/playfair-display": 1705,
  "@fontsource/oswald": 1701,
  "fontsource-roboto-condensed": 1694,
  "@fontsource/jetbrains-mono": 1607,
  "@fontsource/merriweather": 1603,
  "@fontsource/lora": 1570,
  "fontsource-inconsolata": 1543,
  "@fontsource/fira-sans": 1443,
  "@fontsource/pt-sans": 1372,
  "@fontsource/ibm-plex-sans": 1318,
  "fontsource-merriweather": 1311,
  "fontsource-ibm-plex-sans": 1267,
  "fontsource-barlow": 1235,
  "@fontsource/comfortaa": 1234,
  "@fontsource/work-sans": 1200,
  "@fontsource/barlow": 1169,
  "fontsource-nunito": 1167,
  "@fontsource/fira-code": 1140,
  "@fontsource/exo-2": 1076,
  "@fontsource/pt-serif": 1065,
  "@fontsource/ibm-plex-mono": 1037,
  "fontsource-mukta": 1017,
  "@fontsource/metropolis": 1015,
  "fontsource-fira-sans": 998,
  "@fontsource/didact-gothic": 994,
  "@fontsource/pt-mono": 953,
  "fontsource-nunito-sans": 953,
  "fontsource-roboto-slab": 938,
  "@fontsource/source-code-pro": 937,
  "@fontsource/lobster": 934,
  "@fontsource/karla": 912,
  "@fontsource/quicksand": 910,
  "fontsource-baloo-da-2": 888,
  "@fontsource/bitter": 872,
  "@fontsource/alegreya": 872,
  "@fontsource/overpass-mono": 860,
  "@fontsource/ibm-plex-serif": 858,
  "fontsource-metropolis": 842,
  "@fontsource/cormorant-garamond": 817,
  "fontsource-raleway": 806,
  "@fontsource/dm-mono": 803,
  "@fontsource/fira-sans-extra-condensed": 795,
  "@fontsource/yanone-kaffeesatz": 790,
  "@fontsource/prata": 790,
  "@fontsource/arsenal": 784,
  "@fontsource/pt-serif-caption": 781,
  "@fontsource/spectral": 780,
  "@fontsource/old-standard-tt": 778,
  "@fontsource/yeseva-one": 777,
  "@fontsource/pattaya": 774,
  "@fontsource/heebo": 759,
  "fontsource-noto-sans": 751,
  "@fontsource/cabin": 712,
  "@fontsource/mulish": 704,
  "@fontsource/barlow-condensed": 696,
  "@fontsource/jost": 673,
  "@fontsource/inconsolata": 661,
  "@fontsource/libre-franklin": 659,
  "@fontsource/libre-baskerville": 650,
  "@fontsource/manrope": 618,
  "@fontsource/dm-sans": 613,
  "@fontsource/monsieur-la-doulaise": 576,
  "fontsource-bebas-neue": 574,
  "fontsource-bitter": 543,
  "@fontsource/rajdhani": 533,
  "@fontsource/baloo-2": 523,
  "@fontsource/chivo": 513,
  "@fontsource/cedarville-cursive": 502,
  "fontsource-manrope": 497,
  "@fontsource/pacifico": 496,
  "@fontsource/archivo-narrow": 494,
  "fontsource-sen": 485,
  "@fontsource/anton": 485,
  "@fontsource/hind": 484,
  "@fontsource/encode-sans": 477,
  "fontsource-quando": 472,
  "@fontsource/abel": 472,
  "@fontsource/barlow-semi-condensed": 468,
  "@fontsource/bebas-neue": 464,
  "@fontsource/fraunces": 461,
  "@fontsource/sora": 458,
  "@fontsource/piazzolla": 451,
  "fontsource-noto-sans-kr": 447,
  "@fontsource/archivo": 447,
  "fontsource-dm-sans": 441,
  "@fontsource/slabo-27px": 432,
  "@fontsource/krub": 422,
  "fontsource-comfortaa": 420,
  "@fontsource/noto-serif-jp": 413,
  "@fontsource/open-sans-condensed": 402,
  "fontsource-noto-sans-sc": 399,
  "@fontsource/montserrat-alternates": 397,
  "@fontsource/mukta": 396,
  "@fontsource/prompt": 388,
  "fontsource-fugaz-one": 384,
  "fontsource-playfair-display": 376,
  "@fontsource/josefin-sans": 372,
  "@fontsource/public-sans": 371,
  "@fontsource/dosis": 367,
  "@fontsource/titillium-web": 364,
  "@fontsource/source-serif-pro": 364,
  "@fontsource/questrial": 364,
  "@fontsource/unifrakturmaguntia": 361,
  "@fontsource/pt-sans-narrow": 361,
  "@fontsource/jura": 359,
  "@fontsource/marcellus": 354,
  "@fontsource/indie-flower": 353,
  "@fontsource/rokkitt": 350,
  "@fontsource/patua-one": 350,
  "@fontsource/cascadia-code": 350,
  "@fontsource/petit-formal-script": 339,
  "@fontsource/kumbh-sans": 339,
  "@fontsource/tenali-ramakrishna": 334,
  "@fontsource/cabin-condensed": 331,
  "@fontsource/noto-serif": 322,
  "fontsource-ibm-plex-mono": 318,
  "@fontsource/assistant": 318,
  "@fontsource/maven-pro": 314,
  "fontsource-fira-sans-condensed": 312,
  "@fontsource/ubuntu-mono": 307,
  "@fontsource/sarabun": 298,
  "@fontsource/literata": 291,
  "@fontsource/fira-mono": 291,
  "fontsource-quicksand": 290,
  "fontsource-dosis": 290,
  "fontsource-noto-sans-hk": 289,
  "@fontsource/exo": 289,
  "@fontsource/space-grotesk": 284,
  "@fontsource/ibm-plex-sans-condensed": 284,
  "@fontsource/be-vietnam": 282,
  "@fontsource/bodoni-moda": 277,
  "@fontsource/texturina": 272,
  "@fontsource/yellowtail": 270,
  "@fontsource/lexend-deca": 264,
  "@fontsource/gothic-a1": 261,
  "@fontsource/audiowide": 261,
  "@fontsource/imbue": 259,
  "fontsource-lora": 258,
  "fontsource-cooper-hewitt": 257,
  "fontsource-catamaran": 254,
  "@fontsource/fauna-one": 253,
  "fontsource-heebo": 251,
  "@fontsource/handlee": 249,
  "@fontsource/crimson-pro": 248,
  "@fontsource/zilla-slab": 247,
  "@fontsource/space-mono": 242,
  "fontsource-zilla-slab": 241,
  "fontsource-fira-mono": 241,
  "@fontsource/cinzel": 241,
  "fontsource-lexend-peta": 240,
  "@fontsource/signika": 239,
  "fontsource-rosario": 239,
  "fontsource-jura": 238,
  "@fontsource/libre-barcode-ean13-text": 237,
  "@fontsource/judson": 236,
  "fontsource-palanquin": 235,
  "fontsource-oswald": 234,
  "@fontsource/m-plus-1p": 233,
  "@fontsource/merriweather-sans": 232,
  "@fontsource/vollkorn": 231,
  "@fontsource/rosario": 231,
  "@fontsource/cormorant-sc": 229,
  "@fontsource/saira": 228,
  "@fontsource/orbitron": 228,
  "@fontsource/lexend-tera": 228,
  "@fontsource/ballet": 227,
  "fontsource-asap": 226,
  "@fontsource/overpass": 225,
  "@fontsource/libre-caslon-text": 225,
  "@fontsource/lexend-giga": 225,
  "@fontsource/russo-one": 224,
  "@fontsource/catamaran": 224,
  "@fontsource/lexend-mega": 222,
  "@fontsource/arimo": 222,
  "fontsource-jost": 221,
  "@fontsource/slabo-13px": 219,
  "@fontsource/lexend-exa": 219,
  "@fontsource/galada": 219,
  "@fontsource/dancing-script": 219,
  "fontsource-maven-pro": 218,
  "@fontsource/libre-barcode-128": 217,
  "@fontsource/abril-fatface": 217,
  "@fontsource/lexend-zetta": 216,
  "@fontsource/sacramento": 215,
  "@fontsource/laila": 215,
  "@fontsource/teko": 213,
  "@fontsource/m-plus-rounded-1c": 213,
  "@fontsource/eczar": 212,
  "@fontsource/amatic-sc": 212,
  "@fontsource/aleo": 210,
  "@fontsource/quattrocento": 209,
  "fontsource-bungee": 209,
  "fontsource-source-code-pro": 207,
  "@fontsource/lexend-peta": 207,
  "@fontsource/eb-garamond": 207,
  "fontsource-signika": 206,
  "fontsource-material-icons": 206,
  "@fontsource/castoro": 206,
  "fontsource-be-vietnam": 206,
  "fontsource-source-serif-pro": 205,
  "@fontsource/allura": 205,
  "@fontsource/parisienne": 204,
  "fontsource-darker-grotesque": 204,
  "@fontsource/bangers": 204,
  "@fontsource/bree-serif": 203,
  "@fontsource/dm-serif-display": 202,
  "@fontsource/sanchez": 201,
  "@fontsource/libre-barcode-39-extended-text": 200,
  "@fontsource/kosugi": 200,
  "@fontsource/cookie": 200,
  "@fontsource/sintony": 199,
  "@fontsource/libre-barcode-39-extended": 199,
  "@fontsource/libre-barcode-128-text": 199,
  "@fontsource/herr-von-muellerhoff": 199,
  "@fontsource/biorhyme-expanded": 198,
  "@fontsource/oxygen": 197,
  "@fontsource/libre-barcode-39-text": 197,
  "@fontsource/libre-barcode-39": 197,
  "@fontsource/asap": 197,
  "@fontsource/italianno": 196,
  "@fontsource/comic-neue": 196,
  "@fontsource/caveat": 196,
  "fontsource-rajdhani": 195,
  "@fontsource/museomoderno": 194,
  "@fontsource/crimson-text": 193,
  "@fontsource/pragati-narrow": 192,
  "fontsource-bungee-inline": 192,
  "@fontsource/cutive-mono": 191,
  "@fontsource/varela-round": 190,
  "@fontsource/josefin-slab": 190,
  "@fontsource/yusei-magic": 189,
  "@fontsource/ibarra-real-nova": 189,
  "@fontsource/righteous": 188,
  "@fontsource/kanit": 188,
  "@fontsource/arima-madurai": 188,
  "@fontsource/play": 187,
  "@fontsource/hammersmith-one": 187,
  "@fontsource/cousine": 187,
  "@fontsource/commissioner": 187,
  "@fontsource/cairo": 186,
  "@fontsource/petrona": 185,
  "fontsource-bungee-shade": 185,
  "@fontsource/sawarabi-gothic": 184,
  "fontsource-teko": 183,
  "@fontsource/staatliches": 183,
  "@fontsource/poiret-one": 182,
  "@fontsource/monofett": 182,
  "@fontsource/red-hat-display": 180,
  "@fontsource/big-shoulders-display": 180,
  "@fontsource/alike-angular": 180,
  "@fontsource/red-hat-text": 179,
  "fontsource-pt-sans": 179,
  "@fontsource/concert-one": 179,
  "@fontsource/antic-slab": 179,
  "@fontsource/anonymous-pro": 179,
  "@fontsource/satisfy": 178,
  "@fontsource/hepta-slab": 178,
  "@fontsource/andika-new-basic": 178,
  "@fontsource/hind-guntur": 177,
  "@fontsource/acme": 177,
  "@fontsource/tajawal": 176,
  "fontsource-satisfy": 176,
  "@fontsource/podkova": 176,
  "@fontsource/noto-serif-tc": 176,
  "@fontsource/courier-prime": 176,
  "@fontsource/cardo": 176,
  "@fontsource/b612": 176,
  "@fontsource/nobile": 175,
  "fontsource-josefin-sans": 175,
  "@fontsource/domine": 175,
  "@fontsource/unifrakturcook": 174,
  "fontsource-ibm-plex-serif": 174,
  "@fontsource/halant": 174,
  "fontsource-exo-2": 174,
  "@fontsource/abeezee": 174,
  "@fontsource/sunflower": 173,
  "@fontsource/spectral-sc": 173,
  "@fontsource/sawarabi-mincho": 173,
  "@fontsource/philosopher": 173,
  "@fontsource/nanum-brush-script": 173,
  "@fontsource/lily-script-one": 173,
  "@fontsource/happy-monkey": 173,
  "@fontsource/hachi-maru-pop": 173,
  "@fontsource/abhaya-libre": 173,
  "@fontsource/hind-siliguri": 172,
  "@fontsource/hind-madurai": 172,
  "@fontsource/hanuman": 172,
  "@fontsource/black-ops-one": 172,
  "@fontsource/share-tech": 171,
  "@fontsource/quattrocento-sans": 171,
  "@fontsource/pontano-sans": 171,
  "@fontsource/nanum-gothic": 171,
  "@fontsource/krona-one": 171,
  "@fontsource/iceberg": 171,
  "@fontsource/holtwood-one-sc": 171,
  "@fontsource/hind-vadodara": 171,
  "@fontsource/frank-ruhl-libre": 171,
  "@fontsource/balsamiq-sans": 171,
  "@fontsource/trirong": 170,
  "@fontsource/sriracha": 170,
  "@fontsource/newsreader": 170,
  "@fontsource/news-cycle": 170,
  "@fontsource/iceland": 170,
  "@fontsource/hanalei": 170,
  "@fontsource/donegal-one": 170,
  "@fontsource/unica-one": 169,
  "@fontsource/tauri": 169,
  "@fontsource/ribeye-marrow": 169,
  "@fontsource/poor-story": 169,
  "@fontsource/headland-one": 169,
  "@fontsource/fredoka-one": 169,
  "@fontsource/epilogue": 169,
  "@fontsource/alegreya-sans-sc": 169,
  "@fontsource/alegreya-sans": 169,
  "@fontsource/vibur": 168,
  "@fontsource/varela": 168,
  "@fontsource/swanky-and-moo-moo": 168,
  "@fontsource/stalinist-one": 168,
  "@fontsource/siemreap": 168,
  "@fontsource/playfair-display-sc": 168,
  "@fontsource/playball": 168,
  "@fontsource/pirata-one": 168,
  "@fontsource/piedra": 168,
  "fontsource-parisienne": 168,
  "@fontsource/molle": 168,
  "@fontsource/underdog": 167,
  "@fontsource/ubuntu-condensed": 167,
  "@fontsource/turret-road": 167,
  "@fontsource/suranna": 167,
  "@fontsource/sue-ellen-francisco": 167,
  "@fontsource/stardos-stencil": 167,
  "@fontsource/srisakdi": 167,
  "@fontsource/sonsie-one": 167,
  "@fontsource/sniglet": 167,
  "@fontsource/shrikhand": 167,
  "@fontsource/short-stack": 167,
  "@fontsource/ruda": 167,
  "@fontsource/press-start-2p": 167,
  "@fontsource/nanum-gothic-coding": 167,
  "@fontsource/hi-melody": 167,
  "@fontsource/henny-penny": 167,
  "@fontsource/gugi": 167,
  "@fontsource/athiti": 167,
  "@fontsource/arvo": 167,
  "@fontsource/vt323": 166,
  "@fontsource/vibes": 166,
  "@fontsource/vast-shadow": 166,
  "@fontsource/vampiro-one": 166,
  "@fontsource/unkempt": 166,
  "@fontsource/ultra": 166,
  "@fontsource/tinos": 166,
  "@fontsource/telex": 166,
  "@fontsource/sulphur-point": 166,
  "@fontsource/suez-one": 166,
  "@fontsource/strait": 166,
  "@fontsource/stint-ultra-expanded": 166,
  "@fontsource/stoke": 166,
  "@fontsource/sree-krushnadevaraya": 166,
  "@fontsource/song-myung": 166,
  "@fontsource/snowburst-one": 166,
  "@fontsource/signika-negative": 166,
  "fontsource-petit-formal-script": 166,
  "@fontsource/peralta": 166,
  "@fontsource/homenaje": 166,
  "@fontsource/homemade-apple": 166,
  "@fontsource/fira-sans-condensed": 166,
  "@fontsource/faustina": 166,
  "@fontsource/b612-mono": 166,
  "@fontsource/archivo-black": 166,
  "@fontsource/aladin": 166,
  "@fontsource/actor": 166,
  "@fontsource/tomorrow": 165,
  "@fontsource/tangerine": 165,
  "@fontsource/taviraj": 165,
  "@fontsource/suwannaphum": 165,
  "@fontsource/sunshiney": 165,
  "@fontsource/sumana": 165,
  "@fontsource/sigmar-one": 165,
  "@fontsource/shojumaru": 165,
  "@fontsource/share": 165,
  "@fontsource/recursive": 165,
  "@fontsource/pinyon-script": 165,
  "@fontsource/fjalla-one": 165,
  "@fontsource/crete-round": 165,
  "@fontsource/changa": 165,
  "@fontsource/cantarell": 165,
  "@fontsource/big-shoulders-inline-display": 165,
  "@fontsource/alfa-slab-one": 165,
  "@fontsource/tulpen-one": 164,
  "@fontsource/trochut": 164,
  "@fontsource/trocchi": 164,
  "@fontsource/text-me-one": 164,
  "@fontsource/stint-ultra-condensed": 164,
  "@fontsource/skranji": 164,
  "@fontsource/slackey": 164,
  "@fontsource/six-caps": 164,
  "@fontsource/sirin-stencil": 164,
  "@fontsource/shanti": 164,
  "@fontsource/port-lligat-slab": 164,
  "@fontsource/port-lligat-sans": 164,
  "@fontsource/pompiere": 164,
  "@fontsource/poly": 164,
  "@fontsource/gentium-book-basic": 164,
  "@fontsource/big-shoulders-stencil-display": 164,
  "@fontsource/big-shoulders-inline-text": 164,
  "@fontsource/antic": 164,
  "@fontsource/uncial-antiqua": 163,
  "@fontsource/syncopate": 163,
  "@fontsource/stalemate": 163,
  "@fontsource/sofia": 163,
  "@fontsource/simonetta": 163,
  "@fontsource/saira-condensed": 163,
  "@fontsource/pangolin": 163,
  "@fontsource/noto-serif-sc": 163,
  "@fontsource/nanum-myeongjo": 163,
  "@fontsource/hanalei-fill": 163,
  "@fontsource/goldman": 163,
  "@fontsource/cabin-sketch": 163,
  "@fontsource/big-shoulders-stencil-text": 163,
  "@fontsource/akronim": 163,
  "@fontsource/vidaloka": 162,
  "@fontsource/vesper-libre": 162,
  "@fontsource/unna": 162,
  "@fontsource/unlock": 162,
  "@fontsource/syne-mono": 162,
  "@fontsource/supermercado-one": 162,
  "@fontsource/sofadi-one": 162,
  "@fontsource/saira-extra-condensed": 162,
  "@fontsource/grenze-gotisch": 162,
  "@fontsource/averia-sans-libre": 162,
  "@fontsource/trykker": 161,
  "@fontsource/suravaram": 161,
  "@fontsource/sura": 161,
  "@fontsource/smokum": 161,
  "@fontsource/sedgwick-ave": 161,
  "@fontsource/schoolbell": 161,
  "@fontsource/saira-stencil-one": 161,
  "@fontsource/mr-dafoe": 161,
  "@fontsource/grandstander": 161,
  "@fontsource/buda": 161,
  "@fontsource/big-shoulders-text": 161,
  "@fontsource/arapey": 161,
  "@fontsource/alegreya-sc": 161,
  "@fontsource/alata": 161,
  "@fontsource/poller-one": 160,
  "@fontsource/plaster": 160,
  "@fontsource/mystery-quest": 160,
  "@fontsource/markazi-text": 160,
  "@fontsource/londrina-solid": 160,
  "@fontsource/cormorant": 160,
  "@fontsource/contrail-one": 160,
  "@fontsource/coda-caption": 160,
  "@fontsource/clicker-script": 160,
  "@fontsource/bungee": 160,
  "@fontsource/baloo-thambi-2": 160,
  "@fontsource/alex-brush": 160,
  "@fontsource/alef": 160,
  "@fontsource/yantramanav": 159,
  "@fontsource/syne": 159,
  "@fontsource/stylish": 159,
  "@fontsource/solway": 159,
  "@fontsource/shadows-into-light": 159,
  "@fontsource/scheherazade": 159,
  "@fontsource/sansita-swashed": 159,
  "@fontsource/rock-salt": 159,
  "@fontsource/qwigley": 159,
  "@fontsource/quando": 159,
  "@fontsource/patrick-hand": 159,
  "@fontsource/nothing-you-could-do": 159,
  "@fontsource/mukta-malar": 159,
  "@fontsource/monda": 159,
  "@fontsource/miltonian": 159,
  "@fontsource/michroma": 159,
  "@fontsource/great-vibes": 159,
  "fontsource-dm-serif-display": 159,
  "@fontsource/baloo-bhaina-2": 159,
  "@fontsource/snippet": 158,
  "@fontsource/share-tech-mono": 158,
  "@fontsource/sahitya": 158,
  "@fontsource/ruthie": 158,
  "@fontsource/quantico": 158,
  "@fontsource/pt-sans-caption": 158,
  "@fontsource/nosifer": 158,
  "@fontsource/nokora": 158,
  "@fontsource/niramit": 158,
  "@fontsource/neuton": 158,
  "@fontsource/monoton": 158,
  "@fontsource/molengo": 158,
  "@fontsource/metal-mania": 158,
  "@fontsource/meera-inimai": 158,
  "@fontsource/marko-one": 158,
  "@fontsource/manuale": 158,
  "@fontsource/lemonada": 158,
  "@fontsource/im-fell-double-pica": 158,
  "@fontsource/goudy-bookletter-1911": 158,
  "@fontsource/damion": 158,
  "@fontsource/cuprum": 158,
  "@fontsource/corben": 158,
  "@fontsource/bungee-shade": 158,
  "@fontsource/biryani": 158,
  "@fontsource/beth-ellen": 158,
  "@fontsource/battambang": 158,
  "@fontsource/bai-jamjuree": 158,
  "@fontsource/almarai": 158,
  "@fontsource/aldrich": 158,
  "@fontsource/trispace": 157,
  "@fontsource/smythe": 157,
  "@fontsource/single-day": 157,
  "@fontsource/seaweed-script": 157,
  "@fontsource/sarpanch": 157,
  "@fontsource/sarina": 157,
  "@fontsource/sarala": 157,
  "@fontsource/sancreek": 157,
  "@fontsource/ruslan-display": 157,
  "@fontsource/purple-purse": 157,
  "@fontsource/oleo-script": 157,
  "@fontsource/nixie-one": 157,
  "@fontsource/nerko-one": 157,
  "@fontsource/mr-de-haviland": 157,
  "@fontsource/mountains-of-christmas": 157,
  "@fontsource/mitr": 157,
  "@fontsource/miniver": 157,
  "@fontsource/mina": 157,
  "@fontsource/metrophobic": 157,
  "@fontsource/kosugi-maru": 157,
  "@fontsource/glegoo": 157,
  "@fontsource/days-one": 157,
  "@fontsource/black-and-white-picture": 157,
  "@fontsource/baumans": 157,
  "@fontsource/asap-condensed": 157,
  "@fontsource/annie-use-your-telescope": 157,
  "@fontsource/aguafina-script": 157,
  "@fontsource/varta": 156,
  "fontsource-trirong": 156,
  "@fontsource/sansita": 156,
  "@fontsource/salsa": 156,
  "@fontsource/ruge-boogie": 156,
  "@fontsource/rowdies": 156,
  "@fontsource/ropa-sans": 156,
  "@fontsource/noticia-text": 156,
  "@fontsource/norican": 156,
  "@fontsource/niconne": 156,
  "@fontsource/new-rocker": 156,
  "@fontsource/neucha": 156,
  "@fontsource/mukta-mahee": 156,
  "@fontsource/mr-bedfort": 156,
  "@fontsource/mouse-memoirs": 156,
  "@fontsource/moulpali": 156,
  "@fontsource/mogra": 156,
  "@fontsource/mirza": 156,
  "@fontsource/miltonian-tattoo": 156,
  "@fontsource/metal": 156,
  "@fontsource/merienda-one": 156,
  "@fontsource/mali": 156,
  "fontsource-libre-franklin": 156,
  "fontsource-libre-baskerville": 156,
  "@fontsource/langar": 156,
  "@fontsource/kaushan-script": 156,
  "@fontsource/kalam": 156,
  "@fontsource/darker-grotesque": 156,
  "@fontsource/cute-font": 156,
  "@fontsource/calligraffitti": 156,
  "@fontsource/caesar-dressing": 156,
  "@fontsource/buenard": 156,
  "@fontsource/bokor": 156,
  "@fontsource/bellota": 156,
  "@fontsource/atomic-age": 156,
  "@fontsource/angkor": 156,
  "@fontsource/amiri": 156,
  "@fontsource/amarante": 156,
  "@fontsource/allerta": 156,
  "@fontsource/allan": 156,
  "@fontsource/alatsi": 156,
  "@fontsource/xanh-mono": 155,
  "@fontsource/scope-one": 155,
  "@fontsource/sail": 155,
  "@fontsource/quintessential": 155,
  "@fontsource/potta-one": 155,
  "@fontsource/paytone-one": 155,
  "@fontsource/mrs-saint-delafield": 155,
  "@fontsource/mrs-sheppards": 155,
  "@fontsource/moul": 155,
  "@fontsource/montserrat-subrayada": 155,
  "@fontsource/montaga": 155,
  "@fontsource/modak": 155,
  "@fontsource/miss-fajardose": 155,
  "@fontsource/milonga": 155,
  "@fontsource/metamorphous": 155,
  "@fontsource/meie-script": 155,
  "@fontsource/megrim": 155,
  "@fontsource/medula-one": 155,
  "@fontsource/medievalsharp": 155,
  "@fontsource/lateef": 155,
  "@fontsource/kufam": 155,
  "@fontsource/kreon": 155,
  "@fontsource/julius-sans-one": 155,
  "@fontsource/jockey-one": 155,
  "@fontsource/inknut-antiqua": 155,
  "@fontsource/geostar-fill": 155,
  "@fontsource/francois-one": 155,
  "@fontsource/forum": 155,
  "@fontsource/covered-by-your-grace": 155,
  "@fontsource/cormorant-infant": 155,
  "@fontsource/cinzel-decorative": 155,
  "@fontsource/chela-one": 155,
  "@fontsource/chau-philomene-one": 155,
  "@fontsource/bungee-outline": 155,
  "@fontsource/baskervville": 155,
  "@fontsource/bahiana": 155,
  "@fontsource/average": 155,
  "@fontsource/atma": 155,
  "@fontsource/andika": 155,
  "@fontsource/amaranth": 155,
  "@fontsource/allerta-stencil": 155,
  "@fontsource/alike": 155,
  "@fontsource/adamina": 155,
  "@fontsource/proza-libre": 154,
  "@fontsource/prosto-one": 154,
  "@fontsource/notable": 154,
  "@fontsource/mukta-vaani": 154,
  "@fontsource/meddon": 154,
  "@fontsource/gfs-didot": 154,
  "@fontsource/freckle-face": 154,
  "@fontsource/fascinate-inline": 154,
  "@fontsource/encode-sans-condensed": 154,
  "@fontsource/economica": 154,
  "@fontsource/east-sea-dokdo": 154,
  "@fontsource/dm-serif-text": 154,
  "@fontsource/croissant-one": 154,
  "@fontsource/cormorant-upright": 154,
  "@fontsource/chewy": 154,
  "@fontsource/carrois-gothic": 154,
  "@fontsource/cantata-one": 154,
  "@fontsource/calistoga": 154,
  "@fontsource/bungee-inline": 154,
  "@fontsource/black-han-sans": 154,
  "@fontsource/biorhyme": 154,
  "@fontsource/benchnine": 154,
  "@fontsource/bellefair": 154,
  "@fontsource/balthazar": 154,
  "@fontsource/baloo-tammudu-2": 154,
  "@fontsource/baloo-paaji-2": 154,
  "@fontsource/baloo-da-2": 154,
  "@fontsource/baloo-chettan-2": 154,
  "@fontsource/bahianita": 154,
  "@fontsource/bad-script": 154,
  "@fontsource/averia-gruesa-libre": 154,
  "@fontsource/autour-one": 154,
  "@fontsource/asset": 154,
  "@fontsource/aref-ruqaa": 154,
  "@fontsource/architects-daughter": 154,
  "@fontsource/andada": 154,
  "@fontsource/secular-one": 153,
  "@fontsource/rye": 153,
  "@fontsource/rubik-mono-one": 153,
  "@fontsource/red-rose": 153,
  "@fontsource/major-mono-display": 153,
  "@fontsource/mada": 153,
  "@fontsource/kameron": 153,
  "@fontsource/kadwa": 153,
  "@fontsource/istok-web": 153,
  "@fontsource/im-fell-english": 153,
  "@fontsource/im-fell-double-pica-sc": 153,
  "@fontsource/fjord-one": 153,
  "@fontsource/fasthand": 153,
  "@fontsource/esteban": 153,
  "@fontsource/enriqueta": 153,
  "@fontsource/elsie-swash-caps": 153,
  "@fontsource/electrolize": 153,
  "@fontsource/el-messiri": 153,
  "@fontsource/eagle-lake": 153,
  "@fontsource/dorsa": 153,
  "@fontsource/dokdo": 153,
  "@fontsource/denk-one": 153,
  "@fontsource/della-respira": 153,
  "@fontsource/delius-unicase": 153,
  "@fontsource/david-libre": 153,
  "@fontsource/cutive": 153,
  "@fontsource/cormorant-unicase": 153,
  "@fontsource/courgette": 153,
  "@fontsource/condiment": 153,
  "@fontsource/cherry-swash": 153,
  "@fontsource/ceviche-one": 153,
  "@fontsource/carme": 153,
  "@fontsource/candal": 153,
  "@fontsource/cagliostro": 153,
  "@fontsource/bungee-hairline": 153,
  "@fontsource/bubblegum-sans": 153,
  "@fontsource/bowlby-one-sc": 153,
  "@fontsource/bowlby-one": 153,
  "@fontsource/brawler": 153,
  "@fontsource/bigelow-rules": 153,
  "@fontsource/bevan": 153,
  "@fontsource/belleza": 153,
  "@fontsource/bayon": 153,
  "@fontsource/baloo-bhai-2": 153,
  "@fontsource/averia-serif-libre": 153,
  "@fontsource/aubrey": 153,
  "@fontsource/armata": 153,
  "@fontsource/arbutus-slab": 153,
  "@fontsource/almendra-display": 153,
  "@fontsource/alice": 153,
  "@fontsource/advent-pro": 153,
  "@fontsource/aclonica": 153,
  "@fontsource/scada": 152,
  "@fontsource/saira-semi-condensed": 152,
  "@fontsource/merienda": 152,
  "@fontsource/marvel": 152,
  "@fontsource/lobster-two": 152,
  "@fontsource/k2d": 152,
  "@fontsource/just-another-hand": 152,
  "@fontsource/itim": 152,
  "@fontsource/irish-grover": 152,
  "@fontsource/inria-serif": 152,
  "@fontsource/inika": 152,
  "@fontsource/harmattan": 152,
  "@fontsource/gupter": 152,
  "@fontsource/gamja-flower": 152,
  "@fontsource/galindo": 152,
  "@fontsource/galdeano": 152,
  "@fontsource/gaegu": 152,
  "@fontsource/faster-one": 152,
  "@fontsource/farro": 152,
  "@fontsource/fahkwang": 152,
  "@fontsource/encode-sans-semi-expanded": 152,
  "@fontsource/emblema-one": 152,
  "@fontsource/diplomata": 152,
  "@fontsource/creepster": 152,
  "@fontsource/coustard": 152,
  "@fontsource/content": 152,
  "@fontsource/coda": 152,
  "@fontsource/chilanka": 152,
  "@fontsource/chathura": 152,
  "@fontsource/charm": 152,
  "@fontsource/chango": 152,
  "@fontsource/caudex": 152,
  "@fontsource/carter-one": 152,
  "@fontsource/capriola": 152,
  "@fontsource/cantora-one": 152,
  "@fontsource/butcherman": 152,
  "@fontsource/bellota-text": 152,
  "@fontsource/belgrano": 152,
  "@fontsource/baloo-tamma-2": 152,
  "@fontsource/average-sans": 152,
  "@fontsource/astloch": 152,
  "@fontsource/asar": 152,
  "@fontsource/artifika": 152,
  "fontsource-anton": 152,
  "@fontsource/anaheim": 152,
  "@fontsource/amethysta": 152,
  "@fontsource/almendra": 152,
  "@fontsource/truculenta": 151,
  "@fontsource/rum-raisin": 151,
  "@fontsource/rambla": 151,
  "@fontsource/puritan": 151,
  "@fontsource/pridi": 151,
  "@fontsource/odibee-sans": 151,
  "@fontsource/modern-antiqua": 151,
  "@fontsource/leckerli-one": 151,
  "@fontsource/karma": 151,
  "@fontsource/just-me-again-down-here": 151,
  "@fontsource/junge": 151,
  "@fontsource/joti-one": 151,
  "@fontsource/jacques-francois-shadow": 151,
  "@fontsource/jacques-francois": 151,
  "@fontsource/im-fell-french-canon": 151,
  "@fontsource/im-fell-dw-pica-sc": 151,
  "@fontsource/graduate": 151,
  "@fontsource/goblin-one": 151,
  "@fontsource/gochi-hand": 151,
  "@fontsource/germania-one": 151,
  "@fontsource/geostar": 151,
  "@fontsource/geo": 151,
  "@fontsource/fugaz-one": 151,
  "@fontsource/fontdiner-swanky": 151,
  "@fontsource/felipa": 151,
  "@fontsource/erica-one": 151,
  "@fontsource/encode-sans-expanded": 151,
  "@fontsource/duru-sans": 151,
  "@fontsource/do-hyeon": 151,
  "@fontsource/diplomata-sc": 151,
  "@fontsource/crafty-girls": 151,
  "@fontsource/combo": 151,
  "@fontsource/charmonman": 151,
  "@fontsource/cambay": 151,
  "@fontsource/boogaloo": 151,
  "@fontsource/bilbo-swash-caps": 151,
  "@fontsource/barriecito": 151,
  "@fontsource/amiko": 151,
  "@fontsource/zhi-mang-xing": 150,
  "@fontsource/zeyada": 150,
  "@fontsource/voltaire": 150,
  "fontsource-red-hat-text": 150,
  "@fontsource/rancho": 150,
  "@fontsource/oxanium": 150,
  "@fontsource/noto-serif-kr": 150,
  "@fontsource/nanum-pen-script": 150,
  "@fontsource/montez": 150,
  "@fontsource/martel-sans": 150,
  "@fontsource/martel": 150,
  "@fontsource/lilita-one": 150,
  "@fontsource/kelly-slab": 150,
  "@fontsource/kavoon": 150,
  "@fontsource/katibeh": 150,
  "@fontsource/julee": 150,
  "@fontsource/jolly-lodger": 150,
  "@fontsource/jaldi": 150,
  "@fontsource/inder": 150,
  "@fontsource/imprima": 150,
  "@fontsource/im-fell-great-primer": 150,
  "@fontsource/im-fell-english-sc": 150,
  "@fontsource/gilda-display": 150,
  "@fontsource/gidugu": 150,
  "@fontsource/gayathri": 150,
  "@fontsource/gafata": 150,
  "@fontsource/gabriela": 150,
  "@fontsource/fruktur": 150,
  "@fontsource/fresca": 150,
  "@fontsource/freehand": 150,
  "@fontsource/fredericka-the-great": 150,
  "@fontsource/encode-sans-semi-condensed": 150,
  "@fontsource/dr-sugiyama": 150,
  "@fontsource/doppio-one": 150,
  "@fontsource/delius": 150,
  "@fontsource/dawning-of-a-new-day": 150,
  "@fontsource/dangrek": 150,
  "@fontsource/copse": 150,
  "@fontsource/coming-soon": 150,
  "@fontsource/caveat-brush": 150,
  "@fontsource/carrois-gothic-sc": 150,
  "@fontsource/blinker": 150,
  "@fontsource/bilbo": 150,
  "@fontsource/bigshot-one": 150,
  "@fontsource/barrio": 150,
  "@fontsource/antic-didone": 150,
  "@fontsource/yrsa": 149,
  "@fontsource/tienne": 149,
  "@fontsource/syne-tactile": 149,
  "@fontsource/sedgwick-ave-display": 149,
  "@fontsource/reenie-beanie": 149,
  "@fontsource/nova-round": 149,
  "@fontsource/keania-one": 149,
  "@fontsource/kdam-thmor": 149,
  "@fontsource/jim-nightshade": 149,
  "@fontsource/inria-sans": 149,
  "@fontsource/im-fell-great-primer-sc": 149,
  "@fontsource/im-fell-french-canon-sc": 149,
  "@fontsource/im-fell-dw-pica": 149,
  "@fontsource/grenze": 149,
  "@fontsource/gravitas-one": 149,
  "@fontsource/give-you-glory": 149,
  "@fontsource/girassol": 149,
  "@fontsource/gfs-neohellenic": 149,
  "@fontsource/gelasio": 149,
  "@fontsource/flamenco": 149,
  "@fontsource/flavors": 149,
  "@fontsource/federant": 149,
  "@fontsource/emilys-candy": 149,
  "@fontsource/elsie": 149,
  "@fontsource/berkshire-swash": 149,
  "@fontsource/arya": 149,
  "@fontsource/arbutus": 149,
  "@fontsource/almendra-sc": 149,
  "@fontsource/zcool-xiaowei": 148,
  "@fontsource/zcool-kuaile": 148,
  "@fontsource/yeon-sung": 148,
  "@fontsource/yatra-one": 148,
  "@fontsource/waiting-for-the-sunrise": 148,
  "@fontsource/voces": 148,
  "@fontsource/the-girl-next-door": 148,
  "@fontsource/tenor-sans": 148,
  "@fontsource/sorts-mill-goudy": 148,
  "@fontsource/seymour-one": 148,
  "@fontsource/sen": 148,
  "@fontsource/racing-sans-one": 148,
  "@fontsource/padauk": 148,
  "@fontsource/nova-slim": 148,
  "@fontsource/ma-shan-zheng": 148,
  "@fontsource/loved-by-the-king": 148,
  "@fontsource/liu-jian-mao-cao": 148,
  "@fontsource/kantumruy": 148,
  "@fontsource/italiana": 148,
  "@fontsource/habibi": 148,
  "@fontsource/gorditas": 148,
  "@fontsource/gentium-basic": 148,
  "@fontsource/finger-paint": 148,
  "@fontsource/fanwood-text": 148,
  "@fontsource/ewert": 148,
  "@fontsource/englebert": 148,
  "@fontsource/devonshire": 148,
  "@fontsource/dekko": 148,
  "@fontsource/crushed": 148,
  "@fontsource/chicle": 148,
  "@fontsource/cherry-cream-soda": 148,
  "@fontsource/bubbler-one": 148,
  "@fontsource/bentham": 148,
  "@fontsource/amita": 148,
  "@fontsource/warnes": 147,
  "@fontsource/walter-turncoat": 147,
  "@fontsource/viaoda-libre": 147,
  "@fontsource/spicy-rice": 147,
  "@fontsource/shadows-into-light-two": 147,
  "@fontsource/rozha-one": 147,
  "@fontsource/rosarivo": 147,
  "@fontsource/rochester": 147,
  "@fontsource/ravi-prakash": 147,
  "@fontsource/ramabhadra": 147,
  "@fontsource/oranienbaum": 147,
  "@fontsource/odor-mean-chey": 147,
  "@fontsource/ntr": 147,
  "@fontsource/nova-square": 147,
  "@fontsource/nova-oval": 147,
  "@fontsource/nova-mono": 147,
  "@fontsource/miriam-libre": 147,
  "@fontsource/londrina-sketch": 147,
  "@fontsource/londrina-shadow": 147,
  "@fontsource/limelight": 147,
  "@fontsource/kumar-one": 147,
  "@fontsource/kristi": 147,
  "@fontsource/kodchasan": 147,
  "@fontsource/jomolhari": 147,
  "@fontsource/gurajada": 147,
  "@fontsource/griffy": 147,
  "@fontsource/grand-hotel": 147,
  "@fontsource/gotu": 147,
  "@fontsource/frijole": 147,
  "@fontsource/federo": 147,
  "@fontsource/fascinate": 147,
  "@fontsource/euphoria-script": 147,
  "@fontsource/engagement": 147,
  "@fontsource/delius-swash-caps": 147,
  "@fontsource/convergence": 147,
  "@fontsource/chonburi": 147,
  "@fontsource/changa-one": 147,
  "fontsource-cabin": 147,
  "@fontsource/bonbon": 147,
  "@fontsource/basic": 147,
  "fontsource-barlow-condensed": 147,
  "@fontsource/averia-libre": 147,
  "fontsource-alegreya": 147,
  "@fontsource/zilla-slab-highlight": 146,
  "@fontsource/zcool-qingke-huangyou": 146,
  "@fontsource/wire-one": 146,
  "@fontsource/wendy-one": 146,
  "@fontsource/timmana": 146,
  "@fontsource/thasadith": 146,
  "@fontsource/spinnaker": 146,
  "@fontsource/rhodium-libre": 146,
  "@fontsource/peddana": 146,
  "@fontsource/pathway-gothic-one": 146,
  "@fontsource/passero-one": 146,
  "@fontsource/palanquin-dark": 146,
  "@fontsource/oxygen-mono": 146,
  "@fontsource/ovo": 146,
  "@fontsource/overlock": 146,
  "@fontsource/over-the-rainbow": 146,
  "@fontsource/oldenburg": 146,
  "@fontsource/offside": 146,
  "@fontsource/marck-script": 146,
  "@fontsource/maitree": 146,
  "@fontsource/macondo": 146,
  "@fontsource/luckiest-guy": 146,
  "@fontsource/lovers-quarrel": 146,
  "@fontsource/linden-hill": 146,
  "@fontsource/lekton": 146,
  "@fontsource/ledger": 146,
  "@fontsource/lalezar": 146,
  "@fontsource/la-belle-aurore": 146,
  "@fontsource/knewave": 146,
  "@fontsource/jua": 146,
  "@fontsource/jomhuria": 146,
  "@fontsource/gloria-hallelujah": 146,
  "@fontsource/expletus-sans": 146,
  "@fontsource/dhurjati": 146,
  "@fontsource/coiny": 146,
  "@fontsource/codystar": 146,
  "@fontsource/chakra-petch": 146,
  "@fontsource/caladea": 146,
  "@fontsource/butterfly-kids": 146,
  "@fontsource/asul": 146,
  "@fontsource/arizonia": 146,
  "@fontsource/wellfleet": 145,
  "@fontsource/vollkorn-sc": 145,
  "@fontsource/volkhov": 145,
  "@fontsource/viga": 145,
  "@fontsource/tillana": 145,
  "@fontsource/taprom": 145,
  "@fontsource/stick": 145,
  "@fontsource/special-elite": 145,
  "@fontsource/rouge-script": 145,
  "@fontsource/romanesco": 145,
  "@fontsource/rationale": 145,
  "@fontsource/ranga": 145,
  "@fontsource/ranchers": 145,
  "@fontsource/raleway-dots": 145,
  "@fontsource/radley": 145,
  "fontsource-public-sans": 145,
  "@fontsource/prociono": 145,
  "@fontsource/palanquin": 145,
  "@fontsource/overlock-sc": 145,
  "@fontsource/mclaren": 145,
  "@fontsource/mandali": 145,
  "@fontsource/mako": 145,
  "@fontsource/lusitana": 145,
  "@fontsource/lemon": 145,
  "@fontsource/lacquer": 145,
  "@fontsource/khula": 145,
  "@fontsource/khmer": 145,
  "@fontsource/khand": 145,
  "@fontsource/kenia": 145,
  "@fontsource/kavivanar": 145,
  "@fontsource/gruppo": 145,
  "@fontsource/fenix": 145,
  "@fontsource/eater": 145,
  "@fontsource/dynalight": 145,
  "@fontsource/chenla": 145,
  "@fontsource/chelsea-market": 145,
  "@fontsource/cambo": 145,
  "@fontsource/squada-one": 144,
  "@fontsource/spirax": 144,
  "@fontsource/ruluko": 144,
  "@fontsource/revalia": 144,
  "@fontsource/reem-kufi": 144,
  "@fontsource/redressed": 144,
  "@fontsource/ramaraja": 144,
  "@fontsource/preahvihear": 144,
  "@fontsource/patrick-hand-sc": 144,
  "@fontsource/paprika": 144,
  "@fontsource/original-surfer": 144,
  "@fontsource/orienta": 144,
  "@fontsource/nova-cut": 144,
  "@fontsource/mate-sc": 144,
  "@fontsource/mate": 144,
  "@fontsource/marmelad": 144,
  "@fontsource/margarine": 144,
  "@fontsource/mansalva": 144,
  "@fontsource/mallanna": 144,
  "@fontsource/magra": 144,
  "@fontsource/lustria": 144,
  "@fontsource/love-ya-like-a-sister": 144,
  "@fontsource/long-cang": 144,
  "@fontsource/londrina-outline": 144,
  "@fontsource/league-script": 144,
  "@fontsource/lancelot": 144,
  "@fontsource/kurale": 144,
  "@fontsource/kulim-park": 144,
  "@fontsource/kranky": 144,
  "@fontsource/kirang-haerang": 144,
  "@fontsource/fondamento": 144,
  "fontsource-bai-jamjuree": 144,
  "@fontsource/titan-one": 143,
  "@fontsource/risque": 143,
  "@fontsource/ribeye": 143,
  "@fontsource/rasa": 143,
  "@fontsource/maiden-orange": 143,
  "@fontsource/livvic": 143,
  "@fontsource/libre-caslon-display": 143,
  "@fontsource/kumar-one-outline": 143,
  "@fontsource/koulen": 143,
  "@fontsource/farsan": 143,
  "@fontsource/wallpoet": 142,
  "@fontsource/rufina": 142,
  "@fontsource/rammetto-one": 142,
  "@fontsource/rakkas": 142,
  "@fontsource/passion-one": 142,
  "@fontsource/oleo-script-swash-caps": 142,
  "@fontsource/nova-script": 142,
  "@fontsource/marcellus-sc": 142,
  "fontsource-karla": 142,
  "@fontsource/gudea": 142,
  "@fontsource/glass-antiqua": 142,
  "@fontsource/yesteryear": 141,
  "@fontsource/trade-winds": 141,
  "@fontsource/sevillana": 141,
  "@fontsource/pavanam": 141,
  "@fontsource/numans": 141,
  "@fontsource/nova-flat": 141,
  "@fontsource/manjari": 141,
  "@fontsource/macondo-swash-caps": 141,
  "@fontsource/oregano": 140,
  "@fontsource/life-savers": 140,
  "@fontsource/lakki-reddy": 140,
  "@fontsource/kotta-one": 139,
  "@fontsource/kite-one": 139,
  "@fontsource/princess-sofia": 138,
  "@fontsource/koho": 138,
  "fontsource-bangers": 137,
  "fontsource-hind": 135,
  "fontsource-jetbrains-mono": 132,
  "fontsource-gothic-a1": 132,
  "fontsource-news-cycle": 131,
  "fontsource-baloo-paaji-2": 131,
  "fontsource-noto-sans-tc": 130,
  "fontsource-eczar": 129,
  "@fontsource/dotgothic16": 128,
  "@fontsource/reggae-one": 127,
  "fontsource-alata": 127,
  "@fontsource/noto-mono": 125,
  "@fontsource/cooper-hewitt": 125,
  "fontsource-vollkorn": 123,
  "@fontsource/plus-jakarta-sans": 123,
  "fontsource-palanquin-dark": 123,
  "fontsource-red-hat-display": 122,
  "fontsource-domine": 122,
  "fontsource-crimson-text": 122,
  "fontsource-piazzolla": 121,
  "@fontsource/rocknroll-one": 120,
  "fontsource-playfair-display-sc": 120,
  "fontsource-cormorant-garamond": 120,
  "fontsource-noto-serif-jp": 119,
  "fontsource-noticia-text": 119,
  "fontsource-caveat": 119,
  "fontsource-b612": 118,
  "fontsource-share-tech-mono": 117,
  "fontsource-corben": 117,
  "fontsource-pt-serif": 116,
  "fontsource-league-gothic": 116,
  "fontsource-kosugi": 116,
  "@fontsource/benne": 116,
  "fontsource-amiri": 115,
  "fontsource-saira": 113,
  "fontsource-krona-one": 113,
  "@fontsource/league-spartan": 112,
  "fontsource-eb-garamond": 112,
  "fontsource-arimo": 111,
  "fontsource-archivo": 111,
  "@fontsource/aileron": 111,
  "fontsource-josefin-slab": 110,
  "fontsource-caladea": 110,
  "fontsource-baloo-2": 110,
  "fontsource-crimson-pro": 109,
  "fontsource-armata": 109,
  "fontsource-ibarra-real-nova": 108,
  "fontsource-alegreya-sans": 108,
  "@fontsource/shippori-mincho": 107,
  "fontsource-cardo": 107,
  "fontsource-pacifico": 106,
  "fontsource-fjalla-one": 106,
  "fontsource-cuprum": 106,
  "fontsource-cormorant-upright": 106,
  "fontsource-arvo": 106,
  "fontsource-archivo-narrow": 106,
  "fontsource-reenie-beanie": 105,
  "fontsource-encode-sans": 105,
  "fontsource-goudy-bookletter-1911": 104,
  "fontsource-alegreya-sans-sc": 104,
  "@fontsource/clear-sans": 103,
  "fontsource-buenard": 103,
  "fontsource-lexend-deca": 102,
  "fontsource-im-fell-dw-pica": 102,
  "fontsource-harmattan": 102,
  "fontsource-boogaloo": 102,
  "fontsource-big-shoulders-text": 102,
  "fontsource-big-shoulders-display": 102,
  "fontsource-arsenal": 102,
  "fontsource-aref-ruqaa": 102,
  "fontsource-archivo-black": 102,
  "fontsource-alegreya-sc": 102,
  "fontsource-sacramento": 101,
  "@fontsource/league-mono": 101,
  "fontsource-comic-neue": 101,
  "fontsource-cinzel": 101,
  "fontsource-exo": 100,
  "fontsource-encode-sans-expanded": 100,
  "fontsource-cormorant": 100,
  "fontsource-chivo": 100,
  "@fontsource/brygada-1918": 100,
  "@fontsource/akaya-telivigala": 100,
  "fontsource-sulphur-point": 99,
  "fontsource-m-plus-1p": 99,
  "fontsource-kalam": 99,
  "@fontsource/comic-mono": 99,
  "fontsource-cabin-sketch": 99,
  "fontsource-arapey": 99,
  "fontsource-inknut-antiqua": 98,
  "fontsource-elsie": 98,
  "fontsource-cousine": 98,
  "fontsource-cormorant-unicase": 98,
  "fontsource-cormorant-sc": 98,
  "fontsource-cormorant-infant": 98,
  "fontsource-charmonman": 98,
  "fontsource-cabin-condensed": 98,
  "fontsource-bree-serif": 98,
  "fontsource-asap-condensed": 98,
  "fontsource-almarai": 98,
  "fontsource-hammersmith-one": 97,
  "fontsource-firago": 97,
  "fontsource-anonymous-pro": 97,
  "fontsource-hind-vadodara": 96,
  "fontsource-hind-madurai": 96,
  "fontsource-hepta-slab": 96,
  "fontsource-faustina": 96,
  "fontsource-changa": 96,
  "fontsource-cantarell": 96,
  "fontsource-assistant": 96,
  "@fontsource/akaya-kanadaka": 96,
  "@fontsource/oi": 95,
  "fontsource-kanit": 95,
  "fontsource-inria-serif": 95,
  "fontsource-hind-siliguri": 95,
  "fontsource-glegoo": 95,
  "fontsource-gaegu": 95,
  "fontsource-fredericka-the-great": 95,
  "fontsource-expletus-sans": 95,
  "fontsource-balsamiq-sans": 95,
  "fontsource-averia-serif-libre": 95,
  "fontsource-athiti": 95,
  "fontsource-alfa-slab-one": 95,
  "fontsource-inria-sans": 94,
  "fontsource-inika": 94,
  "fontsource-indie-flower": 94,
  "fontsource-homemade-apple": 94,
  "fontsource-gurajada": 94,
  "fontsource-gupter": 94,
  "fontsource-gudea": 94,
  "fontsource-graduate": 94,
  "fontsource-gorditas": 94,
  "fontsource-girassol": 94,
  "fontsource-gidugu": 94,
  "fontsource-gfs-neohellenic": 94,
  "fontsource-gentium-basic": 94,
  "fontsource-gayathri": 94,
  "fontsource-flamenco": 94,
  "fontsource-farro": 94,
  "fontsource-fahkwang": 94,
  "fontsource-enriqueta": 94,
  "fontsource-encode-sans-semi-expanded": 94,
  "fontsource-encode-sans-semi-condensed": 94,
  "fontsource-encode-sans-condensed": 94,
  "fontsource-economica": 94,
  "fontsource-delius-unicase": 94,
  "fontsource-david-libre": 94,
  "fontsource-coustard": 94,
  "fontsource-courier-prime": 94,
  "fontsource-courgette": 94,
  "fontsource-content": 94,
  "fontsource-codystar": 94,
  "fontsource-coda": 94,
  "fontsource-cinzel-decorative": 94,
  "fontsource-chathura": 94,
  "fontsource-chakra-petch": 94,
  "fontsource-caudex": 94,
  "fontsource-cambay": 94,
  "fontsource-blinker": 94,
  "fontsource-biryani": 94,
  "fontsource-biorhyme-expanded": 94,
  "fontsource-biorhyme": 94,
  "fontsource-beth-ellen": 94,
  "fontsource-benchnine": 94,
  "fontsource-bellota": 94,
  "fontsource-battambang": 94,
  "fontsource-barlow-semi-condensed": 94,
  "fontsource-b612-mono": 94,
  "fontsource-averia-sans-libre": 94,
  "fontsource-averia-libre": 94,
  "fontsource-asul": 94,
  "fontsource-astloch": 94,
  "fontsource-arima-madurai": 94,
  "fontsource-amiko": 94,
  "fontsource-amaranth": 94,
  "fontsource-allan": 94,
  "fontsource-aleo": 94,
  "fontsource-advent-pro": 94,
  "fontsource-abril-fatface": 94,
  "fontsource-acme": 94,
  "fontsource-noto-serif": 93,
  "fontsource-marko-one": 93,
  "fontsource-great-vibes": 93,
  "@fontsource/charis-sil": 93,
  "fontsource-allura": 93,
  "fontsource-gloria-hallelujah": 92,
  "fontsource-didact-gothic": 92,
  "fontsource-covered-by-your-grace": 92,
  "fontsource-cairo": 92,
  "fontsource-audiowide": 92,
  "fontsource-aguafina-script": 92,
  "fontsource-abeezee": 92,
  "fontsource-im-fell-english": 91,
  "fontsource-holtwood-one-sc": 91,
  "fontsource-hanalei": 91,
  "fontsource-gfs-didot": 91,
  "fontsource-fruktur": 91,
  "fontsource-fredoka-one": 91,
  "fontsource-forum": 91,
  "fontsource-duru-sans": 91,
  "fontsource-combo": 91,
  "fontsource-chelsea-market": 91,
  "fontsource-ceviche-one": 91,
  "@fontsource/blackout-two-am": 91,
  "@fontsource/blackout-midnight": 91,
  "fontsource-bad-script": 91,
  "fontsource-antic-slab": 91,
  "@fontsource/yakuhanjp": 90,
  "fontsource-quattrocento-sans": 90,
  "fontsource-lobster": 90,
  "fontsource-kantumruy": 90,
  "@fontsource/junction": 90,
  "fontsource-judson": 90,
  "fontsource-istok-web": 90,
  "fontsource-inder": 90,
  "fontsource-imprima": 90,
  "fontsource-im-fell-great-primer-sc": 90,
  "fontsource-im-fell-french-canon": 90,
  "fontsource-im-fell-english-sc": 90,
  "fontsource-im-fell-dw-pica-sc": 90,
  "fontsource-iceland": 90,
  "fontsource-iceberg": 90,
  "fontsource-homenaje": 90,
  "fontsource-herr-von-muellerhoff": 90,
  "fontsource-headland-one": 90,
  "fontsource-handlee": 90,
  "fontsource-hanalei-fill": 90,
  "fontsource-habibi": 90,
  "fontsource-griffy": 90,
  "fontsource-grand-hotel": 90,
  "fontsource-goblin-one": 90,
  "fontsource-glass-antiqua": 90,
  "fontsource-give-you-glory": 90,
  "fontsource-gilda-display": 90,
  "fontsource-geostar-fill": 90,
  "fontsource-geostar": 90,
  "fontsource-geo": 90,
  "fontsource-galindo": 90,
  "fontsource-galdeano": 90,
  "fontsource-gafata": 90,
  "fontsource-gabriela": 90,
  "fontsource-freckle-face": 90,
  "fontsource-flavors": 90,
  "fontsource-fondamento": 90,
  "fontsource-fontdiner-swanky": 90,
  "fontsource-fjord-one": 90,
  "fontsource-fira-sans-extra-condensed": 90,
  "fontsource-finger-paint": 90,
  "fontsource-federo": 90,
  "fontsource-felipa": 90,
  "fontsource-federant": 90,
  "fontsource-fauna-one": 90,
  "fontsource-fasthand": 90,
  "fontsource-faster-one": 90,
  "fontsource-fascinate": 90,
  "fontsource-farsan": 90,
  "fontsource-fanwood-text": 90,
  "fontsource-ewert": 90,
  "fontsource-esteban": 90,
  "fontsource-euphoria-script": 90,
  "fontsource-erica-one": 90,
  "fontsource-englebert": 90,
  "fontsource-engagement": 90,
  "fontsource-emblema-one": 90,
  "fontsource-eater": 90,
  "fontsource-eagle-lake": 90,
  "fontsource-dynalight": 90,
  "fontsource-dorsa": 90,
  "fontsource-dr-sugiyama": 90,
  "fontsource-doppio-one": 90,
  "fontsource-donegal-one": 90,
  "fontsource-diplomata-sc": 90,
  "fontsource-devonshire": 90,
  "fontsource-denk-one": 90,
  "fontsource-della-respira": 90,
  "fontsource-delius-swash-caps": 90,
  "fontsource-delius": 90,
  "fontsource-days-one": 90,
  "fontsource-dekko": 90,
  "fontsource-dawning-of-a-new-day": 90,
  "fontsource-cutive-mono": 90,
  "fontsource-cutive": 90,
  "fontsource-crushed": 90,
  "fontsource-creepster": 90,
  "fontsource-crafty-girls": 90,
  "fontsource-copse": 90,
  "fontsource-cookie": 90,
  "fontsource-convergence": 90,
  "fontsource-contrail-one": 90,
  "fontsource-condiment": 90,
  "fontsource-concert-one": 90,
  "fontsource-coiny": 90,
  "fontsource-chonburi": 90,
  "fontsource-chilanka": 90,
  "fontsource-chicle": 90,
  "fontsource-chewy": 90,
  "fontsource-cherry-cream-soda": 90,
  "fontsource-chenla": 90,
  "fontsource-chau-philomene-one": 90,
  "fontsource-chango": 90,
  "fontsource-changa-one": 90,
  "fontsource-cedarville-cursive": 90,
  "fontsource-caveat-brush": 90,
  "fontsource-carrois-gothic": 90,
  "fontsource-carme": 90,
  "fontsource-cantora-one": 90,
  "fontsource-cantata-one": 90,
  "fontsource-capriola": 90,
  "fontsource-candal": 90,
  "fontsource-cambo": 90,
  "fontsource-calligraffitti": 90,
  "fontsource-calistoga": 90,
  "fontsource-cagliostro": 90,
  "fontsource-butcherman": 90,
  "fontsource-butterfly-kids": 90,
  "fontsource-bungee-outline": 90,
  "fontsource-bungee-hairline": 90,
  "fontsource-bubblegum-sans": 90,
  "fontsource-bubbler-one": 90,
  "fontsource-brawler": 90,
  "fontsource-bowlby-one-sc": 90,
  "fontsource-bowlby-one": 90,
  "fontsource-bokor": 90,
  "fontsource-bonbon": 90,
  "fontsource-black-ops-one": 90,
  "@fontsource/blackout-sunrise": 90,
  "fontsource-bilbo": 90,
  "fontsource-bigelow-rules": 90,
  "fontsource-bentham": 90,
  "fontsource-belleza": 90,
  "fontsource-bellefair": 90,
  "fontsource-belgrano": 90,
  "fontsource-baumans": 90,
  "fontsource-barrio": 90,
  "fontsource-balthazar": 90,
  "fontsource-baloo-tammudu-2": 90,
  "fontsource-baloo-tamma-2": 90,
  "fontsource-baloo-chettan-2": 90,
  "fontsource-baloo-bhaina-2": 90,
  "fontsource-bahianita": 90,
  "fontsource-bahiana": 90,
  "fontsource-average-sans": 90,
  "fontsource-averia-gruesa-libre": 90,
  "fontsource-average": 90,
  "fontsource-autour-one": 90,
  "fontsource-aubrey": 90,
  "fontsource-atomic-age": 90,
  "fontsource-asset": 90,
  "fontsource-artifika": 90,
  "fontsource-arizonia": 90,
  "fontsource-architects-daughter": 90,
  "fontsource-arbutus-slab": 90,
  "fontsource-arbutus": 90,
  "fontsource-antic-didone": 90,
  "fontsource-antic": 90,
  "fontsource-annie-use-your-telescope": 90,
  "fontsource-andika": 90,
  "fontsource-anaheim": 90,
  "fontsource-amatic-sc": 90,
  "fontsource-amarante": 90,
  "fontsource-almendra-sc": 90,
  "fontsource-allerta-stencil": 90,
  "fontsource-allerta": 90,
  "fontsource-alike-angular": 90,
  "fontsource-alice": 90,
  "fontsource-alex-brush": 90,
  "fontsource-alike": 90,
  "fontsource-aldrich": 90,
  "fontsource-aladin": 90,
  "fontsource-alatsi": 90,
  "fontsource-akronim": 90,
  "fontsource-adamina": 90,
  "fontsource-actor": 90,
  "fontsource-aclonica": 90,
  "fontsource-jomhuria": 89,
  "fontsource-italianno": 89,
  "fontsource-im-fell-double-pica": 89,
  "@fontsource/firago": 89,
  "@fontsource/dseg7": 89,
  "@fontsource/dseg14": 89,
  "@fontsource/cascadia-mono": 89,
  "@fontsource/vazir": 88,
  "@fontsource/shippori-mincho-b1": 88,
  "fontsource-literata": 88,
  "fontsource-libre-barcode-128-text": 88,
  "@fontsource/dseg-weather": 88,
  "fontsource-russo-one": 87,
  "fontsource-oxygen": 87,
  "fontsource-m-plus-rounded-1c": 87,
  "fontsource-just-another-hand": 87,
  "fontsource-julius-sans-one": 87,
  "fontsource-jolly-lodger": 87,
  "fontsource-jim-nightshade": 87,
  "fontsource-do-hyeon": 87,
  "@fontsource/chunk-five": 87,
  "fontsource-cascadia-code": 87,
  "fontsource-spartan": 86,
  "fontsource-merriweather-sans": 86,
  "fontsource-kameron": 86,
  "fontsource-just-me-again-down-here": 86,
  "fontsource-joti-one": 86,
  "fontsource-jomolhari": 86,
  "fontsource-jockey-one": 86,
  "fontsource-jacques-francois-shadow": 86,
  "fontsource-jacques-francois": 86,
  "fontsource-italiana": 86,
  "fontsource-irish-grover": 86,
  "fontsource-gugi": 86,
  "fontsource-gotu": 86,
  "fontsource-gamja-flower": 86,
  "fontsource-frank-ruhl-libre": 86,
  "fontsource-east-sea-dokdo": 86,
  "fontsource-black-han-sans": 86,
  "@fontsource/league-gothic": 84,
  "fontsource-dancing-script": 84,
  "@fontsource/yakuhanmp": 83,
  "@fontsource/yakuhanjps": 83,
  "@fontsource/victor-mono": 83,
  "fontsource-limelight": 83,
  "fontsource-lexend-mega": 83,
  "fontsource-lexend-exa": 83,
  "@fontsource/karmilla": 83,
  "fontsource-katibeh": 83,
  "fontsource-itim": 83,
  "fontsource-abel": 83,
  "fontsource-museomoderno": 82,
  "fontsource-mukta-mahee": 82,
  "fontsource-lexend-zetta": 82,
  "fontsource-lexend-tera": 82,
  "fontsource-lexend-giga": 82,
  "fontsource-khula": 82,
  "fontsource-kdam-thmor": 82,
  "fontsource-karma": 82,
  "fontsource-kadwa": 82,
  "fontsource-dm-mono": 82,
  "@fontsource/yakuhanrps": 81,
  "fontsource-yanone-kaffeesatz": 81,
  "fontsource-space-mono": 81,
  "fontsource-michroma": 81,
  "fontsource-krub": 81,
  "fontsource-kaushan-script": 81,
  "fontsource-epilogue": 81,
  "@fontsource/yakuhanrp": 80,
  "@fontsource/syne-italic": 80,
  "fontsource-prompt": 80,
  "@fontsource/ostrich-sans": 80,
  "@fontsource/ostrich-sans-rounded": 80,
  "fontsource-montserrat-alternates": 80,
  "fontsource-lekton": 80,
  "@fontsource/league-mono-narrow": 80,
  "@fontsource/league-mono-extended": 80,
  "@fontsource/yakuhanmps": 79,
  "@fontsource/ostrich-sans-inline": 79,
  "@fontsource/ostrich-sans-dashed": 79,
  "fontsource-mr-de-haviland": 79,
  "@fontsource/league-mono-wide": 79,
  "fontsource-khmer": 79,
  "fontsource-montserrat-subrayada": 78,
  "fontsource-londrina-solid": 78,
  "fontsource-libre-caslon-text": 78,
  "@fontsource/league-mono-condensed": 78,
  "fontsource-lalezar": 78,
  "fontsource-laila": 78,
  "fontsource-kulim-park": 78,
  "fontsource-koho": 78,
  "fontsource-khand": 78,
  "fontsource-kelly-slab": 78,
  "fontsource-mirza": 77,
  "fontsource-lobster-two": 77,
  "fontsource-electrolize": 77,
  "fontsource-questrial": 76,
  "fontsource-orbitron": 76,
  "@fontsource/league-gothic-condensed": 76,
  "fontsource-kotta-one": 76,
  "fontsource-markazi-text": 75,
  "fontsource-manuale": 75,
  "fontsource-love-ya-like-a-sister": 75,
  "fontsource-kurale": 75,
  "fontsource-hind-guntur": 75,
  "fontsource-gelasio": 75,
  "fontsource-el-messiri": 75,
  "fontsource-chunk-five": 75,
  "fontsource-cascadia-mono": 75,
  "fontsource-blackout-midnight": 75,
  "fontsource-amita": 75,
  "fontsource-quattrocento": 74,
  "fontsource-nobile": 74,
  "fontsource-manjari": 74,
  "fontsource-lustria": 74,
  "fontsource-londrina-shadow": 74,
  "fontsource-londrina-outline": 74,
  "fontsource-lily-script-one": 74,
  "fontsource-lilita-one": 74,
  "fontsource-libre-caslon-display": 74,
  "fontsource-libre-barcode-39-text": 74,
  "fontsource-libre-barcode-39-extended-text": 74,
  "fontsource-libre-barcode-39-extended": 74,
  "fontsource-leckerli-one": 74,
  "fontsource-league-script": 74,
  "fontsource-lateef": 74,
  "fontsource-lancelot": 74,
  "fontsource-lakki-reddy": 74,
  "fontsource-lacquer": 74,
  "fontsource-kumar-one-outline": 74,
  "fontsource-kumar-one": 74,
  "fontsource-kristi": 74,
  "fontsource-kranky": 74,
  "fontsource-koulen": 74,
  "fontsource-knewave": 74,
  "fontsource-kite-one": 74,
  "fontsource-kenia": 74,
  "fontsource-junction": 74,
  "fontsource-dseg7": 74,
  "fontsource-dseg-weather": 74,
  "fontsource-blackout-two-am": 74,
  "fontsource-blackout-sunrise": 74,
  "fontsource-baloo-bhai-2": 74,
  "fontsource-notable": 73,
  "fontsource-nanum-myeongjo": 73,
  "fontsource-mukta-vaani": 73,
  "fontsource-mrs-sheppards": 73,
  "fontsource-mr-dafoe": 73,
  "fontsource-mr-bedfort": 73,
  "fontsource-mountains-of-christmas": 73,
  "fontsource-monda": 73,
  "fontsource-miriam-libre": 73,
  "fontsource-mina": 73,
  "fontsource-merienda": 73,
  "fontsource-marvel": 73,
  "fontsource-martel-sans": 73,
  "fontsource-martel": 73,
  "fontsource-mali": 73,
  "fontsource-maitree": 73,
  "fontsource-magra": 73,
  "fontsource-mada": 73,
  "fontsource-loved-by-the-king": 73,
  "fontsource-londrina-sketch": 73,
  "fontsource-linden-hill": 73,
  "fontsource-kreon": 73,
  "fontsource-ibm-plex-sans-condensed": 73,
  "fontsource-halant": 73,
  "fontsource-baskervville": 73,
  "fontsource-alef": 73,
  "fontsource-abhaya-libre": 73,
  "fontsource-nokora": 72,
  "fontsource-nanum-gothic": 72,
  "fontsource-hanuman": 72,
  "fontsource-grenze": 72,
  "fontsource-gentium-book-basic": 72,
  "fontsource-elsie-swash-caps": 72,
  "fontsource-cherry-swash": 72,
  "fontsource-charm": 72,
  "fontsource-bellota-text": 72,
  "fontsource-atma": 72,
  "fontsource-arya": 72,
  "fontsource-almendra": 72,
  "fontsource-molle": 71,
  "fontsource-major-mono-display": 71,
  "fontsource-lusitana": 71,
  "fontsource-la-belle-aurore": 71,
  "fontsource-francois-one": 71,
  "fontsource-crete-round": 71,
  "fontsource-montez": 70,
  "fontsource-mitr": 70,
  "fontsource-metamorphous": 70,
  "fontsource-megrim": 70,
  "fontsource-medula-one": 70,
  "fontsource-long-cang": 70,
  "fontsource-libre-barcode-128": 70,
  "fontsource-kosugi-maru": 70,
  "fontsource-kirang-haerang": 70,
  "fontsource-andada": 70,
  "fontsource-nosifer": 69,
  "fontsource-nixie-one": 69,
  "fontsource-niconne": 69,
  "fontsource-nanum-gothic-coding": 69,
  "fontsource-mystery-quest": 69,
  "fontsource-mouse-memoirs": 69,
  "fontsource-moulpali": 69,
  "fontsource-molengo": 69,
  "fontsource-mogra": 69,
  "fontsource-modern-antiqua": 69,
  "fontsource-miniver": 69,
  "fontsource-miltonian-tattoo": 69,
  "fontsource-miltonian": 69,
  "fontsource-milonga": 69,
  "fontsource-metrophobic": 69,
  "fontsource-metal-mania": 69,
  "fontsource-merienda-one": 69,
  "fontsource-meie-script": 69,
  "fontsource-meera-inimai": 69,
  "fontsource-meddon": 69,
  "fontsource-mclaren": 69,
  "fontsource-mate-sc": 69,
  "fontsource-mate": 69,
  "fontsource-marcellus-sc": 69,
  "fontsource-mansalva": 69,
  "fontsource-mallanna": 69,
  "fontsource-macondo-swash-caps": 69,
  "fontsource-macondo": 69,
  "fontsource-livvic": 69,
  "fontsource-liu-jian-mao-cao": 69,
  "fontsource-k2d": 69,
  "fontsource-jaldi": 69,
  "fontsource-im-fell-great-primer": 69,
  "fontsource-im-fell-french-canon-sc": 69,
  "fontsource-im-fell-double-pica-sc": 69,
  "fontsource-henny-penny": 69,
  "fontsource-happy-monkey": 69,
  "fontsource-gruppo": 69,
  "fontsource-gravitas-one": 69,
  "fontsource-gochi-hand": 69,
  "fontsource-germania-one": 69,
  "fontsource-galada": 69,
  "fontsource-frijole": 69,
  "fontsource-fresca": 69,
  "fontsource-freehand": 69,
  "fontsource-fenix": 69,
  "fontsource-fascinate-inline": 69,
  "fontsource-emilys-candy": 69,
  "fontsource-diplomata": 69,
  "fontsource-dhurjati": 69,
  "fontsource-dangrek": 69,
  "fontsource-damion": 69,
  "fontsource-croissant-one": 69,
  "fontsource-coming-soon": 69,
  "fontsource-coda-caption": 69,
  "fontsource-clicker-script": 69,
  "fontsource-chela-one": 69,
  "fontsource-carrois-gothic-sc": 69,
  "fontsource-carter-one": 69,
  "fontsource-caesar-dressing": 69,
  "fontsource-buda": 69,
  "fontsource-bilbo-swash-caps": 69,
  "fontsource-bigshot-one": 69,
  "fontsource-bevan": 69,
  "fontsource-berkshire-swash": 69,
  "fontsource-bayon": 69,
  "fontsource-basic": 69,
  "fontsource-barriecito": 69,
  "fontsource-baloo-thambi-2": 69,
  "fontsource-asar": 69,
  "fontsource-angkor": 69,
  "fontsource-amethysta": 69,
  "fontsource-almendra-display": 69,
  "fontsource-nothing-you-could-do": 68,
  "fontsource-norican": 68,
  "fontsource-new-rocker": 68,
  "fontsource-nanum-pen-script": 68,
  "fontsource-maiden-orange": 68,
  "fontsource-league-spartan": 68,
  "fontsource-dm-serif-text": 67,
  "fontsource-prata": 66,
  "fontsource-karmilla": 66,
  "fontsource-junge": 66,
  "fontsource-julee": 66,
  "fontsource-hi-melody": 66,
  "fontsource-dokdo": 66,
  "fontsource-cute-font": 66,
  "fontsource-black-and-white-picture": 66,
  "fontsource-nanum-brush-script": 65,
  "fontsource-mandali": 65,
  "fontsource-ma-shan-zheng": 65,
  "fontsource-noto-serif-kr": 64,
  "fontsource-modak": 64,
  "fontsource-jua": 63,
  "fontsource-rock-salt": 62,
  "fontsource-oxanium": 62,
  "fontsource-lemonada": 62,
  "fontsource-pt-mono": 61,
  "fontsource-passion-one": 61,
  "fontsource-keania-one": 61,
  "fontsource-ubuntu-mono": 60,
  "fontsource-neucha": 60,
  "fontsource-monsieur-la-doulaise": 60,
  "fontsource-life-savers": 60,
  "fontsource-ledger": 60,
  "fontsource-kodchasan": 60,
  "fontsource-kavoon": 60,
  "fontsource-kavivanar": 60,
  "fontsource-unna": 59,
  "fontsource-mukta-malar": 59,
  "fontsource-league-gothic-condensed": 59,
  "fontsource-grenze-gotisch": 59,
  "fontsource-zilla-slab-highlight": 58,
  "fontsource-wire-one": 58,
  "fontsource-vesper-libre": 58,
  "fontsource-righteous": 58,
  "fontsource-open-sans-condensed": 58,
  "fontsource-league-mono-wide": 58,
  "fontsource-league-mono-narrow": 58,
  "fontsource-league-mono-extended": 58,
  "fontsource-league-mono-condensed": 58,
  "fontsource-league-mono": 58,
  "fontsource-luckiest-guy": 57,
  "fontsource-libre-barcode-39": 57,
  "fontsource-lemon": 57,
  "fontsource-dseg14": 57,
  "fontsource-zeyada": 56,
  "fontsource-tinos": 56,
  "fontsource-slabo-27px": 56,
  "fontsource-scheherazade": 56,
  "fontsource-poiret-one": 56,
  "fontsource-philosopher": 56,
  "fontsource-noto-serif-tc": 56,
  "fontsource-niramit": 56,
  "fontsource-neuton": 56,
  "fontsource-mrs-saint-delafield": 56,
  "fontsource-monoton": 56,
  "fontsource-marcellus": 56,
  "fontsource-lovers-quarrel": 56,
  "fontsource-spectral": 55,
  "fontsource-sawarabi-mincho": 55,
  "fontsource-rubik-mono-one": 55,
  "fontsource-rokkitt": 55,
  "fontsource-overpass-mono": 55,
  "fontsource-marck-script": 55,
  "fontsource-yantramanav": 54,
  "fontsource-rufina": 54,
  "fontsource-ruda": 54,
  "fontsource-oleo-script": 54,
  "fontsource-noto-serif-sc": 54,
  "fontsource-montaga": 54,
  "fontsource-vt323": 53,
  "fontsource-tangerine": 53,
  "fontsource-staatliches": 53,
  "fontsource-sofia": 53,
  "fontsource-snowburst-one": 53,
  "fontsource-sniglet": 53,
  "fontsource-scada": 53,
  "fontsource-pt-sans-narrow": 53,
  "fontsource-permanent-marker": 53,
  "fontsource-moul": 53,
  "fontsource-monofett": 53,
  "fontsource-miss-fajardose": 53,
  "fontsource-metal": 53,
  "fontsource-medievalsharp": 53,
  "fontsource-marmelad": 53,
  "fontsource-margarine": 53,
  "fontsource-mako": 53,
  "fontsource-yrsa": 52,
  "fontsource-volkhov": 52,
  "fontsource-vollkorn-sc": 52,
  "fontsource-trochut": 52,
  "fontsource-trade-winds": 52,
  "fontsource-tienne": 52,
  "fontsource-tenor-sans": 52,
  "fontsource-taviraj": 52,
  "fontsource-suravaram": 52,
  "fontsource-sumana": 52,
  "fontsource-srisakdi": 52,
  "fontsource-solway": 52,
  "fontsource-skranji": 52,
  "fontsource-sintony": 52,
  "fontsource-simonetta": 52,
  "fontsource-signika-negative": 52,
  "fontsource-share": 52,
  "fontsource-sarpanch": 52,
  "fontsource-sarabun": 52,
  "fontsource-sansita": 52,
  "fontsource-sahitya": 52,
  "fontsource-reem-kufi": 52,
  "fontsource-rasa": 52,
  "fontsource-ranga": 52,
  "fontsource-rakkas": 52,
  "fontsource-puritan": 52,
  "fontsource-proza-libre": 52,
  "fontsource-pridi": 52,
  "fontsource-play": 52,
  "fontsource-playball": 52,
  "fontsource-padauk": 52,
  "fontsource-overlock": 52,
  "fontsource-oleo-script-swash-caps": 52,
  "fontsource-ntr": 52,
  "fontsource-special-elite": 51,
  "fontsource-saira-extra-condensed": 51,
  "fontsource-press-start-2p": 51,
  "fontsource-nova-mono": 51,
  "fontsource-ubuntu-condensed": 50,
  "fontsource-trispace": 50,
  "fontsource-share-tech": 50,
  "fontsource-racing-sans-one": 50,
  "fontsource-patrick-hand": 50,
  "fontsource-wallpoet": 49,
  "fontsource-vast-shadow": 49,
  "fontsource-unifrakturmaguntia": 49,
  "fontsource-unica-one": 49,
  "fontsource-trocchi": 49,
  "fontsource-sunshiney": 49,
  "fontsource-sigmar-one": 49,
  "fontsource-ruthie": 49,
  "fontsource-rye": 49,
  "fontsource-raleway-dots": 49,
  "fontsource-pontano-sans": 49,
  "fontsource-poller-one": 49,
  "fontsource-plaster": 49,
  "fontsource-pattaya": 49,
  "fontsource-oxygen-mono": 49,
  "fontsource-ovo": 49,
  "fontsource-oregano": 49,
  "fontsource-oranienbaum": 49,
  "fontsource-original-surfer": 49,
  "fontsource-orienta": 49,
  "fontsource-odor-mean-chey": 49,
  "fontsource-odibee-sans": 49,
  "fontsource-numans": 49,
  "fontsource-nova-round": 49,
  "fontsource-nova-oval": 49,
  "fontsource-nova-flat": 49,
  "fontsource-nova-cut": 49,
  "@fontsource/carlito": 49,
  "fontsource-yesteryear": 48,
  "fontsource-yeseva-one": 48,
  "fontsource-yellowtail": 48,
  "fontsource-wendy-one": 48,
  "fontsource-wellfleet": 48,
  "fontsource-warnes": 48,
  "fontsource-walter-turncoat": 48,
  "fontsource-waiting-for-the-sunrise": 48,
  "fontsource-voces": 48,
  "fontsource-viga": 48,
  "fontsource-vibur": 48,
  "fontsource-viaoda-libre": 48,
  "fontsource-vampiro-one": 48,
  "fontsource-unlock": 48,
  "fontsource-unifrakturcook": 48,
  "fontsource-underdog": 48,
  "fontsource-uncial-antiqua": 48,
  "fontsource-ultra": 48,
  "fontsource-tulpen-one": 48,
  "fontsource-trykker": 48,
  "fontsource-titan-one": 48,
  "fontsource-timmana": 48,
  "fontsource-the-girl-next-door": 48,
  "fontsource-tenali-ramakrishna": 48,
  "fontsource-telex": 48,
  "fontsource-taprom": 48,
  "fontsource-tajawal": 48,
  "fontsource-syne": 48,
  "fontsource-swanky-and-moo-moo": 48,
  "fontsource-suwannaphum": 48,
  "fontsource-sunflower": 48,
  "fontsource-sue-ellen-francisco": 48,
  "fontsource-strait": 48,
  "fontsource-stint-ultra-expanded": 48,
  "fontsource-stint-ultra-condensed": 48,
  "fontsource-stalemate": 48,
  "fontsource-stalinist-one": 48,
  "fontsource-sree-krushnadevaraya": 48,
  "fontsource-squada-one": 48,
  "fontsource-spirax": 48,
  "fontsource-spinnaker": 48,
  "fontsource-spicy-rice": 48,
  "fontsource-spectral-sc": 48,
  "fontsource-sorts-mill-goudy": 48,
  "fontsource-sonsie-one": 48,
  "fontsource-smokum": 48,
  "fontsource-smythe": 48,
  "fontsource-slackey": 48,
  "fontsource-slabo-13px": 48,
  "fontsource-six-caps": 48,
  "fontsource-sirin-stencil": 48,
  "fontsource-single-day": 48,
  "fontsource-siemreap": 48,
  "fontsource-shrikhand": 48,
  "fontsource-short-stack": 48,
  "fontsource-shojumaru": 48,
  "fontsource-shadows-into-light-two": 48,
  "fontsource-shadows-into-light": 48,
  "fontsource-seymour-one": 48,
  "fontsource-sevillana": 48,
  "fontsource-sedgwick-ave": 48,
  "fontsource-sedgwick-ave-display": 48,
  "fontsource-secular-one": 48,
  "fontsource-seaweed-script": 48,
  "fontsource-scope-one": 48,
  "fontsource-schoolbell": 48,
  "fontsource-sarina": 48,
  "fontsource-sarala": 48,
  "fontsource-sancreek": 48,
  "fontsource-sanchez": 48,
  "fontsource-salsa": 48,
  "fontsource-saira-stencil-one": 48,
  "fontsource-sail": 48,
  "fontsource-ruslan-display": 48,
  "fontsource-rum-raisin": 48,
  "fontsource-ruluko": 48,
  "fontsource-rozha-one": 48,
  "fontsource-rouge-script": 48,
  "fontsource-rosarivo": 48,
  "fontsource-ropa-sans": 48,
  "fontsource-romanesco": 48,
  "fontsource-risque": 48,
  "fontsource-revalia": 48,
  "fontsource-ribeye-marrow": 48,
  "fontsource-rhodium-libre": 48,
  "fontsource-ravi-prakash": 48,
  "fontsource-rationale": 48,
  "fontsource-rancho": 48,
  "fontsource-ranchers": 48,
  "fontsource-ramaraja": 48,
  "fontsource-ramabhadra": 48,
  "fontsource-radley": 48,
  "fontsource-qwigley": 48,
  "fontsource-quintessential": 48,
  "fontsource-purple-purse": 48,
  "fontsource-pt-serif-caption": 48,
  "fontsource-prosto-one": 48,
  "fontsource-princess-sofia": 48,
  "fontsource-port-lligat-slab": 48,
  "fontsource-port-lligat-sans": 48,
  "fontsource-pompiere": 48,
  "fontsource-poly": 48,
  "fontsource-pirata-one": 48,
  "fontsource-pinyon-script": 48,
  "fontsource-petrona": 48,
  "fontsource-peralta": 48,
  "fontsource-peddana": 48,
  "fontsource-patua-one": 48,
  "fontsource-patrick-hand-sc": 48,
  "fontsource-pathway-gothic-one": 48,
  "fontsource-passero-one": 48,
  "fontsource-paprika": 48,
  "fontsource-pangolin": 48,
  "fontsource-over-the-rainbow": 48,
  "fontsource-oldenburg": 48,
  "fontsource-nova-square": 48,
  "fontsource-nova-slim": 48,
  "@fontsource/mononoki": 48,
  "fontsource-ruge-boogie": 47,
  "fontsource-zhi-mang-xing": 44,
  "fontsource-zcool-xiaowei": 44,
  "fontsource-zcool-qingke-huangyou": 44,
  "fontsource-zcool-kuaile": 44,
  "fontsource-varela": 44,
  "fontsource-sura": 44,
  "fontsource-stylish": 44,
  "fontsource-song-myung": 44,
  "fontsource-poor-story": 44,
  "fontsource-varela-round": 43,
  "fontsource-pragati-narrow": 43,
  "fontsource-paytone-one": 43,
  "fontsource-aileron": 43,
  "fontsource-yatra-one": 42,
  "fontsource-sansita-swashed": 42,
  "fontsource-red-rose": 42,
  "fontsource-podkova": 42,
  "fontsource-syncopate": 41,
  "fontsource-grandstander": 41,
  "fontsource-vibes": 40,
  "fontsource-unkempt": 40,
  "fontsource-turret-road": 40,
  "fontsource-tomorrow": 40,
  "fontsource-tillana": 40,
  "fontsource-thasadith": 40,
  "fontsource-stoke": 40,
  "fontsource-stardos-stencil": 40,
  "fontsource-sawarabi-gothic": 40,
  "fontsource-saira-semi-condensed": 40,
  "fontsource-saira-condensed": 40,
  "fontsource-recursive": 40,
  "fontsource-rambla": 40,
  "fontsource-quantico": 40,
  "fontsource-pt-sans-caption": 40,
  "fontsource-old-standard-tt": 40,
  "fontsource-nova-script": 39,
  "fontsource-overlock-sc": 38,
  "fontsource-voltaire": 37,
  "fontsource-vidaloka": 37,
  "fontsource-text-me-one": 37,
  "fontsource-tauri": 37,
  "fontsource-suranna": 37,
  "fontsource-supermercado-one": 37,
  "fontsource-suez-one": 37,
  "fontsource-sofadi-one": 37,
  "fontsource-snippet": 37,
  "fontsource-shanti": 37,
  "fontsource-rochester": 37,
  "fontsource-ribeye": 37,
  "fontsource-redressed": 37,
  "fontsource-rammetto-one": 37,
  "fontsource-prociono": 37,
  "fontsource-preahvihear": 37,
  "fontsource-piedra": 37,
  "fontsource-pavanam": 37,
  "fontsource-offside": 37,
  "fontsource-commissioner": 37,
  "fontsource-varta": 36,
  "fontsource-sora": 36,
  "fontsource-space-grotesk": 35,
  "fontsource-yeon-sung": 34,
  "fontsource-sriracha": 34,
  "fontsource-clear-sans": 34,
  "fontsource-syne-italic": 33,
  "fontsource-ostrich-sans-inline": 33,
  "fontsource-ostrich-sans": 33,
  "fontsource-goldman": 33,
  "fontsource-yakuhanrps": 32,
  "fontsource-yakuhanrp": 32,
  "fontsource-yakuhanmps": 32,
  "fontsource-yakuhanmp": 32,
  "fontsource-yakuhanjps": 32,
  "fontsource-victor-mono": 32,
  "fontsource-rowdies": 32,
  "fontsource-ostrich-sans-dashed": 32,
  "fontsource-ostrich-sans-rounded": 32,
  "fontsource-kufam": 32,
  "fontsource-castoro": 31,
  "fontsource-charis-sil": 30,
  "fontsource-big-shoulders-stencil-display": 30,
  "fontsource-big-shoulders-stencil-text": 30,
  "fontsource-big-shoulders-inline-display": 30,
  "fontsource-big-shoulders-inline-text": 30,
  "fontsource-kumbh-sans": 29,
  "fontsource-andika-new-basic": 29,
  "fontsource-syne-mono": 28,
  "fontsource-yakuhanjp": 25,
  "fontsource-vazir": 25,
  "fontsource-langar": 25,
  "fontsource-texturina": 24,
  "fontsource-nerko-one": 22,
  "fontsource-libre-barcode-ean13-text": 21,
  "fontsource-xanh-mono": 18,
  "fontsource-syne-tactile": 16
}
